starlette_apitally/__init__.py
starlette_apitally/metrics.py
starlette_apitally/middleware.py
starlette_apitally-0.0.1.dist-info/LICENSE
starlette_apitally-0.0.1.dist-info/METADATA
starlette_apitally-0.0.1.dist-info/WHEEL
starlette_apitally-0.0.1.dist-info/RECORD
