Metadata-Version: 2.1
Name: starlette-apitally
Version: 0.0.1
Summary: Apitally integration for Starlette
Home-page: https://github.com/apitally/starlette-apitally
License: MIT
Author: Simon Gurcke
Author-email: simon@gurcke.de
Requires-Python: >=3.9,<4.0
Classifier: License :: OSI Approved :: MIT License
Classifier: Programming Language :: Python :: 3
Classifier: Programming Language :: Python :: 3.9
Classifier: Programming Language :: Python :: 3.10
Classifier: Programming Language :: Python :: 3.11
Requires-Dist: backoff (>=1.11.0)
Requires-Dist: httpx (>=0.18.0)
Requires-Dist: starlette (>=0.15.0)
Project-URL: Repository, https://github.com/apitally/starlette-apitally
